{
"meta":{"test_sets":[],"test_metrics":[],"learn_metrics":[{"best_value":"Min","name":"Logloss"}],"launch_mode":"Train","parameters":"","iteration_count":100,"learn_sets":["learn"],"name":"experiment"},
"iterations":[
{"learn":[0.4866784949],"iteration":0,"passed_time":3.456492824,"remaining_time":342.1927896},
{"learn":[0.369668723],"iteration":1,"passed_time":3.646925955,"remaining_time":178.6993718},
{"learn":[0.3173354382],"iteration":2,"passed_time":3.719187986,"remaining_time":120.2537449},
{"learn":[0.2882422222],"iteration":3,"passed_time":3.792806546,"remaining_time":91.02735711},
{"learn":[0.2778146246],"iteration":4,"passed_time":3.941937775,"remaining_time":74.89681773},
{"learn":[0.2664000477],"iteration":5,"passed_time":4.028941873,"remaining_time":63.12008935},
{"learn":[0.2601674937],"iteration":6,"passed_time":4.086407018,"remaining_time":54.2908361},
{"learn":[0.253928408],"iteration":7,"passed_time":4.165340729,"remaining_time":47.90141838},
{"learn":[0.2419754942],"iteration":8,"passed_time":4.235105344,"remaining_time":42.8216207},
{"learn":[0.2382115548],"iteration":9,"passed_time":4.309501275,"remaining_time":38.78551148},
{"learn":[0.2361854941],"iteration":10,"passed_time":4.364482044,"remaining_time":35.31262745},
{"learn":[0.2311849593],"iteration":11,"passed_time":4.44127623,"remaining_time":32.56935902},
{"learn":[0.2293758299],"iteration":12,"passed_time":4.511529335,"remaining_time":30.19254248},
{"learn":[0.2283567009],"iteration":13,"passed_time":4.582329171,"remaining_time":28.14859348},
{"learn":[0.2262934992],"iteration":14,"passed_time":4.672065916,"remaining_time":26.47504019},
{"learn":[0.2245616778],"iteration":15,"passed_time":4.770034372,"remaining_time":25.04268046},
{"learn":[0.2221743708],"iteration":16,"passed_time":4.827376852,"remaining_time":23.56895757},
{"learn":[0.2211363774],"iteration":17,"passed_time":4.890411748,"remaining_time":22.27854241},
{"learn":[0.2197363075],"iteration":18,"passed_time":4.994972032,"remaining_time":21.29435445},
{"learn":[0.2187197557],"iteration":19,"passed_time":5.08092847,"remaining_time":20.32371388},
{"learn":[0.2169304368],"iteration":20,"passed_time":5.157082489,"remaining_time":19.40045317},
{"learn":[0.2151808475],"iteration":21,"passed_time":5.234527955,"remaining_time":18.55878093},
{"learn":[0.2146309118],"iteration":22,"passed_time":5.304323744,"remaining_time":17.75795341},
{"learn":[0.2136286293],"iteration":23,"passed_time":5.396290397,"remaining_time":17.08825293},
{"learn":[0.2128376483],"iteration":24,"passed_time":5.466329337,"remaining_time":16.39898801},
{"learn":[0.2114850537],"iteration":25,"passed_time":5.538854339,"remaining_time":15.76443158},
{"learn":[0.21031131],"iteration":26,"passed_time":5.606029309,"remaining_time":15.15704221},
{"learn":[0.2093400162],"iteration":27,"passed_time":5.676582674,"remaining_time":14.59692688},
{"learn":[0.2085724053],"iteration":28,"passed_time":5.749194373,"remaining_time":14.07561381},
{"learn":[0.2067310619],"iteration":29,"passed_time":5.810379579,"remaining_time":13.55755235},
{"learn":[0.2054192935],"iteration":30,"passed_time":5.909484934,"remaining_time":13.15336969},
{"learn":[0.2047868726],"iteration":31,"passed_time":5.986877322,"remaining_time":12.72211431},
{"learn":[0.2042851653],"iteration":32,"passed_time":6.046932581,"remaining_time":12.27710554},
{"learn":[0.2029374516],"iteration":33,"passed_time":6.104340478,"remaining_time":11.8496021},
{"learn":[0.2014496882],"iteration":34,"passed_time":6.177624142,"remaining_time":11.47273055},
{"learn":[0.2004845503],"iteration":35,"passed_time":6.229642901,"remaining_time":11.07492071},
{"learn":[0.1999170065],"iteration":36,"passed_time":6.28781274,"remaining_time":10.70627575},
{"learn":[0.1983885827],"iteration":37,"passed_time":6.364650369,"remaining_time":10.38442955},
{"learn":[0.1976325538],"iteration":38,"passed_time":6.424551093,"remaining_time":10.04865684},
{"learn":[0.196872743],"iteration":39,"passed_time":6.49356832,"remaining_time":9.74035248},
{"learn":[0.1960593257],"iteration":40,"passed_time":6.570420189,"remaining_time":9.454994906},
{"learn":[0.1951873975],"iteration":41,"passed_time":6.637308325,"remaining_time":9.165806734},
{"learn":[0.1951362813],"iteration":42,"passed_time":6.714752701,"remaining_time":8.900951255},
{"learn":[0.1942491415],"iteration":43,"passed_time":6.820690281,"remaining_time":8.680878539},
{"learn":[0.1934789344],"iteration":44,"passed_time":6.88420009,"remaining_time":8.414022332},
{"learn":[0.1917009735],"iteration":45,"passed_time":6.947477247,"remaining_time":8.15573416},
{"learn":[0.1906638043],"iteration":46,"passed_time":7.020586937,"remaining_time":7.916832078},
{"learn":[0.1899714806],"iteration":47,"passed_time":7.086894181,"remaining_time":7.677468696},
{"learn":[0.1886279732],"iteration":48,"passed_time":7.152423218,"remaining_time":7.44435886},
{"learn":[0.1883050808],"iteration":49,"passed_time":7.229628834,"remaining_time":7.229628834},
{"learn":[0.1882451338],"iteration":50,"passed_time":7.310168994,"remaining_time":7.0234957},
{"learn":[0.1868356905],"iteration":51,"passed_time":7.388738617,"remaining_time":6.820374108},
{"learn":[0.1862594289],"iteration":52,"passed_time":7.466331868,"remaining_time":6.621086751},
{"learn":[0.1847233294],"iteration":53,"passed_time":7.54087215,"remaining_time":6.423705905},
{"learn":[0.1847031788],"iteration":54,"passed_time":7.608705616,"remaining_time":6.225304595},
{"learn":[0.1839552022],"iteration":55,"passed_time":7.680125459,"remaining_time":6.034384289},
{"learn":[0.1835069895],"iteration":56,"passed_time":7.768347212,"remaining_time":5.860332107},
{"learn":[0.1827971511],"iteration":57,"passed_time":7.83296322,"remaining_time":5.67214578},
{"learn":[0.1822537004],"iteration":58,"passed_time":7.900309004,"remaining_time":5.49004524},
{"learn":[0.1818356507],"iteration":59,"passed_time":7.986439561,"remaining_time":5.324293041},
{"learn":[0.180362478],"iteration":60,"passed_time":8.06035642,"remaining_time":5.153342629},
{"learn":[0.1790569341],"iteration":61,"passed_time":8.118576177,"remaining_time":4.975901528},
{"learn":[0.1786055812],"iteration":62,"passed_time":8.181863534,"remaining_time":4.805221441},
{"learn":[0.1779891513],"iteration":63,"passed_time":8.258897587,"remaining_time":4.645629893},
{"learn":[0.1772234237],"iteration":64,"passed_time":8.327729816,"remaining_time":4.484162209},
{"learn":[0.1761854377],"iteration":65,"passed_time":8.381595166,"remaining_time":4.317791449},
{"learn":[0.1757318071],"iteration":66,"passed_time":8.452102323,"remaining_time":4.162975771},
{"learn":[0.1753279954],"iteration":67,"passed_time":8.509697113,"remaining_time":4.004563347},
{"learn":[0.1746284918],"iteration":68,"passed_time":8.579913121,"remaining_time":3.854743576},
{"learn":[0.1745234221],"iteration":69,"passed_time":8.636962481,"remaining_time":3.701555349},
{"learn":[0.1737009228],"iteration":70,"passed_time":8.677123215,"remaining_time":3.544177088},
{"learn":[0.173265384],"iteration":71,"passed_time":8.725889416,"remaining_time":3.39340144},
{"learn":[0.1726361149],"iteration":72,"passed_time":8.783817604,"remaining_time":3.248809251},
{"learn":[0.1722602169],"iteration":73,"passed_time":8.824901573,"remaining_time":3.100641093},
{"learn":[0.1705165531],"iteration":74,"passed_time":8.878199635,"remaining_time":2.959399878},
{"learn":[0.1698189484],"iteration":75,"passed_time":8.925220391,"remaining_time":2.81849065},
{"learn":[0.1693830596],"iteration":76,"passed_time":8.966982165,"remaining_time":2.678449218},
{"learn":[0.1689384528],"iteration":77,"passed_time":9.024416742,"remaining_time":2.545348312},
{"learn":[0.1672934575],"iteration":78,"passed_time":9.076675182,"remaining_time":2.412787074},
{"learn":[0.1672383503],"iteration":79,"passed_time":9.125348248,"remaining_time":2.281337062},
{"learn":[0.1667251046],"iteration":80,"passed_time":9.188939804,"remaining_time":2.155430324},
{"learn":[0.1660294337],"iteration":81,"passed_time":9.233122657,"remaining_time":2.026783022},
{"learn":[0.1653803342],"iteration":82,"passed_time":9.273052631,"remaining_time":1.899299936},
{"learn":[0.1648367838],"iteration":83,"passed_time":9.319263098,"remaining_time":1.775097733},
{"learn":[0.1642987917],"iteration":84,"passed_time":9.359606377,"remaining_time":1.651695243},
{"learn":[0.1640153892],"iteration":85,"passed_time":9.394249597,"remaining_time":1.529296446},
{"learn":[0.1635459132],"iteration":86,"passed_time":9.427392374,"remaining_time":1.408690815},
{"learn":[0.1627896581],"iteration":87,"passed_time":9.462607449,"remaining_time":1.290355561},
{"learn":[0.1621188186],"iteration":88,"passed_time":9.495092962,"remaining_time":1.173550815},
{"learn":[0.1617063631],"iteration":89,"passed_time":9.528784449,"remaining_time":1.058753828},
{"learn":[0.1614513866],"iteration":90,"passed_time":9.566119329,"remaining_time":0.9460997139},
{"learn":[0.160857772],"iteration":91,"passed_time":9.596947513,"remaining_time":0.8345171751},
{"learn":[0.1603539333],"iteration":92,"passed_time":9.629719985,"remaining_time":0.7248176332},
{"learn":[0.160345923],"iteration":93,"passed_time":9.660910325,"remaining_time":0.6166538505},
{"learn":[0.159677954],"iteration":94,"passed_time":9.695926562,"remaining_time":0.5103119243},
{"learn":[0.1592814378],"iteration":95,"passed_time":9.727533127,"remaining_time":0.4053138803},
{"learn":[0.1587679401],"iteration":96,"passed_time":9.755347555,"remaining_time":0.30171178},
{"learn":[0.1580522081],"iteration":97,"passed_time":9.783501189,"remaining_time":0.1996632896},
{"learn":[0.1573514014],"iteration":98,"passed_time":9.814657951,"remaining_time":0.0991379591},
{"learn":[0.1572847553],"iteration":99,"passed_time":9.840999807,"remaining_time":0}
]}time":0}
]}_time":0}
]}